.gitignore
.gitlab-ci.yml
COC.md
COMMIT_EMOJI_CHEATSHEET.md
LICENSE.txt
MANIFEST.in
README.md
environ.py.dist
manage.py
requirements.txt
run.sh
settings.py
setup.py
test.sh
urls.py
docs/mkdocs.yml
docs/docs/index.md
drf_auto_endpoint/__init__.py
drf_auto_endpoint/app_settings.py
drf_auto_endpoint/endpoints.py
drf_auto_endpoint/factories.py
drf_auto_endpoint/metadata.py
drf_auto_endpoint/router.py
drf_auto_endpoint.egg-info/PKG-INFO
drf_auto_endpoint.egg-info/SOURCES.txt
drf_auto_endpoint.egg-info/dependency_links.txt
drf_auto_endpoint.egg-info/requires.txt
drf_auto_endpoint.egg-info/top_level.txt
drf_auto_endpoint/migrations/__init__.py
sample/__init__.py
sample/models.py
sample/views.py
sample/wsgi.py
sample/migrations/0001_initial.py
sample/migrations/0002_howitworks.py
sample/migrations/0003_product_product_type.py
sample/migrations/__init__.py
sample/tests/__init__.py
sample/tests/base.py
sample/tests/data.py
sample/tests/factories.py
sample/tests/tests_functional.py
sample/tests/tests_unit.py